rage/rage.py
rage/value.py
rage/__init__.py
rage-0.1.0.dist-info/DESCRIPTION.rst
rage-0.1.0.dist-info/METADATA
rage-0.1.0.dist-info/metadata.json
rage-0.1.0.dist-info/RECORD
rage-0.1.0.dist-info/top_level.txt
rage-0.1.0.dist-info/WHEEL
