Metadata-Version: 2.0
Name: rage
Version: 0.1.0
Summary: Windows Registry Manipulation
Home-page: https://github.com/tmr232/rage
Author: Tamir Bahar
Author-email: UNKNOWN
License: MIT
Platform: UNKNOWN
